[
    {
        "case": 0,
        "collider1": {
            "type": "Box",
            "collider2origin": [
                [
                    0.907778172512869,
                    0.4194505805326725,
                    0.0,
                    -1.612083837096907
                ],
                [
                    -0.4194505805326725,
                    0.907778172512869,
                    0.0,
                    -0.24654756573714753
                ],
                [
                    0.0,
                    0.0,
                    1.0,
                    -0.040000000000000036
                ],
                [
                    0.0,
                    0.0,
                    0.0,
                    1.0
                ]
            ],
            "size": [
                2.0,
                2.0,
                2.0
            ]
        },
        "collider2": {
            "type": "Box",
            "collider2origin": [
                [
                    0.38430911434457193,
                    -0.6874117132393925,
                    0.6162561489615939,
                    -0.3096118353897385
                ],
                [
                    -0.3637546617131203,
                    -0.7262679508760754,
                    -0.5832815868962778,
                    1.1567550282064418
                ],
                [
                    0.8485216854704798,
                    -5.6169205498598175e-06,
                    -0.5291606081850633,
                    -0.996424653612009
                ],
                [
                    0.0,
                    0.0,
                    0.0,
                    1.0
                ]
            ],
            "size": [
                0.09102,
                0.10007,
                0.11882
            ]
        },
        "distance": 0.749003837174356
    },
    {
        "case": 1,
        "collider1": {
            "type": "Box",
            "collider2origin": [
                [
                    0.907778172512869,
                    0.4194505805326725,
                    0.0,
                    -1.612083837096907
                ],
                [
                    -0.4194505805326725,
                    0.907778172512869,
                    0.0,
                    -0.24654756573714753
                ],
                [
                    0.0,
                    0.0,
                    1.0,
                    -0.040000000000000036
                ],
                [
                    0.0,
                    0.0,
                    0.0,
                    1.0
                ]
            ],
            "size": [
                2.0,
                2.0,
                2.0
            ]
        },
        "collider2": {
            "type": "Box",
            "collider2origin": [
                [
                    -0.7749027540330632,
                    0.14054921080888275,
                    0.6162561489615939,
                    -0.24461871575191324
                ],
                [
                    -0.3291793354027072,
                    0.7425789894223994,
                    -0.5832815868962778,
                    1.0915971077334832
                ],
                [
                    -0.5395986350388645,
                    -0.6548452976157102,
                    -0.5291606081850633,
                    -1.05556012217584
                ],
                [
                    0.0,
                    0.0,
                    0.0,
                    1.0
                ]
            ],
            "size": [
                0.09126,
                0.11887,
                0.10009
            ]
        },
        "distance": 0.7032723651918892
    },
    {
        "case": 2,
        "collider1": {
            "type": "Box",
            "collider2origin": [
                [
                    0.9077781725128689,
                    0.4194505805326724,
                    0.0,
                    0.4158817547107895
                ],
                [
                    -0.4194505805326724,
                    0.9077781725128689,
                    0.0,
                    0.733173894971941
                ],
                [
                    0.0,
                    0.0,
                    1.0,
                    -0.6599999999999999
                ],
                [
                    0.0,
                    0.0,
                    0.0,
                    1.0
                ]
            ],
            "size": [
                0.6,
                1.0,
                0.8
            ]
        },
        "collider2": {
            "type": "Box",
            "collider2origin": [
                [
                    0.41794797548152757,
                    -0.6874161585807079,
                    -0.5939516097402511,
                    0.0018090081761367172
                ],
                [
                    -0.395585572966582,
                    -0.7262637433389149,
                    0.5621859386111037,
                    0.8419148044646755
                ],
                [
                    -0.8178212177802635,
                    -5.787033172304953e-06,
                    -0.5754723761527712,
                    -0.2752442090068187
                ],
                [
                    0.0,
                    0.0,
                    0.0,
                    1.0
                ]
            ],
            "size": [
                0.15068,
                0.17726,
                0.74884
            ]
        },
        "distance": 0.0
    },
    {
        "case": 3,
        "collider1": {
            "type": "Box",
            "collider2origin": [
                [
                    0.9077781725128689,
                    0.4194505805326724,
                    0.0,
                    0.27063700059322826
                ],
                [
                    -0.4194505805326724,
                    0.9077781725128689,
                    0.0,
                    0.8002854543438492
                ],
                [
                    0.0,
                    0.0,
                    1.0,
                    -0.25
                ],
                [
                    0.0,
                    0.0,
                    0.0,
                    1.0
                ]
            ],
            "size": [
                0.2,
                0.2,
                0.02
            ]
        },
        "collider2": {
            "type": "Box",
            "collider2origin": [
                [
                    0.41794797548152757,
                    -0.6874161585807079,
                    -0.5939516097402511,
                    0.0018090081761367172
                ],
                [
                    -0.395585572966582,
                    -0.7262637433389149,
                    0.5621859386111037,
                    0.8419148044646755
                ],
                [
                    -0.8178212177802635,
                    -5.787033172304953e-06,
                    -0.5754723761527712,
                    -0.2752442090068187
                ],
                [
                    0.0,
                    0.0,
                    0.0,
                    1.0
                ]
            ],
            "size": [
                0.15068,
                0.17726,
                0.74884
            ]
        },
        "distance": 0.0
    },
    {
        "case": 4,
        "collider1": {
            "type": "Box",
            "collider2origin": [
                [
                    0.907778172512869,
                    0.4194505805326725,
                    0.0,
                    -1.612083837096907
                ],
                [
                    -0.4194505805326725,
                    0.907778172512869,
                    0.0,
                    -0.24654756573714753
                ],
                [
                    0.0,
                    0.0,
                    1.0,
                    -0.040000000000000036
                ],
                [
                    0.0,
                    0.0,
                    0.0,
                    1.0
                ]
            ],
            "size": [
                2.0,
                2.0,
                2.0
            ]
        },
        "collider2": {
            "type": "Box",
            "collider2origin": [
                [
                    0.41794797548152757,
                    -0.6874161585807079,
                    -0.5939516097402511,
                    0.0018090081761367172
                ],
                [
                    -0.395585572966582,
                    -0.7262637433389149,
                    0.5621859386111037,
                    0.8419148044646755
                ],
                [
                    -0.8178212177802635,
                    -5.787033172304953e-06,
                    -0.5754723761527712,
                    -0.2752442090068187
                ],
                [
                    0.0,
                    0.0,
                    0.0,
                    1.0
                ]
            ],
            "size": [
                0.15068,
                0.17726,
                0.74884
            ]
        },
        "distance": 0.5442822943759481
    },
    {
        "case": 5,
        "collider1": {
            "type": "Box",
            "collider2origin": [
                [
                    0.907778172512869,
                    0.4194505805326725,
                    0.0,
                    -0.7418785952877999
                ],
                [
                    -0.4194505805326725,
                    0.907778172512869,
                    0.0,
                    1.2791466490804724
                ],
                [
                    0.0,
                    0.0,
                    1.0,
                    0.27
                ],
                [
                    0.0,
                    0.0,
                    0.0,
                    1.0
                ]
            ],
            "size": [
                0.52,
                1.16,
                0.6
            ]
        },
        "collider2": {
            "type": "Box",
            "collider2origin": [
                [
                    0.41794797548152757,
                    -0.6874161585807079,
                    -0.5939516097402511,
                    0.0018090081761367172
                ],
                [
                    -0.395585572966582,
                    -0.7262637433389149,
                    0.5621859386111037,
                    0.8419148044646755
                ],
                [
                    -0.8178212177802635,
                    -5.787033172304953e-06,
                    -0.5754723761527712,
                    -0.2752442090068187
                ],
                [
                    0.0,
                    0.0,
                    0.0,
                    1.0
                ]
            ],
            "size": [
                0.15068,
                0.17726,
                0.74884
            ]
        },
        "distance": 0.4628668995212986
    },
    {
        "case": 6,
        "collider1": {
            "type": "Box",
            "collider2origin": [
                [
                    0.9077781725128689,
                    0.4194505805326724,
                    0.0,
                    0.4158817547107895
                ],
                [
                    -0.4194505805326724,
                    0.9077781725128689,
                    0.0,
                    0.733173894971941
                ],
                [
                    0.0,
                    0.0,
                    1.0,
                    -0.6599999999999999
                ],
                [
                    0.0,
                    0.0,
                    0.0,
                    1.0
                ]
            ],
            "size": [
                0.6,
                1.0,
                0.8
            ]
        },
        "collider2": {
            "type": "Box",
            "collider2origin": [
                [
                    0.41794797548152757,
                    -0.6874161585807079,
                    -0.5939516097402511,
                    0.0018090081761367172
                ],
                [
                    -0.395585572966582,
                    -0.7262637433389149,
                    0.5621859386111037,
                    0.8419148044646755
                ],
                [
                    -0.8178212177802635,
                    -5.787033172304953e-06,
                    -0.5754723761527712,
                    -0.2752442090068187
                ],
                [
                    0.0,
                    0.0,
                    0.0,
                    1.0
                ]
            ],
            "size": [
                0.15068,
                0.17726,
                0.74884
            ]
        },
        "distance": 0.0
    },
    {
        "case": 7,
        "collider1": {
            "type": "Box",
            "collider2origin": [
                [
                    0.9077781725128689,
                    0.4194505805326724,
                    0.0,
                    0.27063700059322826
                ],
                [
                    -0.4194505805326724,
                    0.9077781725128689,
                    0.0,
                    0.8002854543438492
                ],
                [
                    0.0,
                    0.0,
                    1.0,
                    -0.25
                ],
                [
                    0.0,
                    0.0,
                    0.0,
                    1.0
                ]
            ],
            "size": [
                0.2,
                0.2,
                0.02
            ]
        },
        "collider2": {
            "type": "Box",
            "collider2origin": [
                [
                    0.41794797548152757,
                    -0.6874161585807079,
                    -0.5939516097402511,
                    0.0018090081761367172
                ],
                [
                    -0.395585572966582,
                    -0.7262637433389149,
                    0.5621859386111037,
                    0.8419148044646755
                ],
                [
                    -0.8178212177802635,
                    -5.787033172304953e-06,
                    -0.5754723761527712,
                    -0.2752442090068187
                ],
                [
                    0.0,
                    0.0,
                    0.0,
                    1.0
                ]
            ],
            "size": [
                0.15068,
                0.17726,
                0.74884
            ]
        },
        "distance": 0.0
    },
    {
        "case": 8,
        "collider1": {
            "type": "Box",
            "collider2origin": [
                [
                    0.907778172512869,
                    0.4194505805326725,
                    0.0,
                    -1.612083837096907
                ],
                [
                    -0.4194505805326725,
                    0.907778172512869,
                    0.0,
                    -0.24654756573714753
                ],
                [
                    0.0,
                    0.0,
                    1.0,
                    -0.040000000000000036
                ],
                [
                    0.0,
                    0.0,
                    0.0,
                    1.0
                ]
            ],
            "size": [
                2.0,
                2.0,
                2.0
            ]
        },
        "collider2": {
            "type": "Box",
            "collider2origin": [
                [
                    0.41794797548152757,
                    -0.6874161585807079,
                    -0.5939516097402511,
                    0.0018090081761367172
                ],
                [
                    -0.395585572966582,
                    -0.7262637433389149,
                    0.5621859386111037,
                    0.8419148044646755
                ],
                [
                    -0.8178212177802635,
                    -5.787033172304953e-06,
                    -0.5754723761527712,
                    -0.2752442090068187
                ],
                [
                    0.0,
                    0.0,
                    0.0,
                    1.0
                ]
            ],
            "size": [
                0.15068,
                0.17726,
                0.74884
            ]
        },
        "distance": 0.5442822943759481
    },
    {
        "case": 9,
        "collider1": {
            "type": "Box",
            "collider2origin": [
                [
                    0.907778172512869,
                    0.4194505805326725,
                    0.0,
                    -0.7418785952877999
                ],
                [
                    -0.4194505805326725,
                    0.907778172512869,
                    0.0,
                    1.2791466490804724
                ],
                [
                    0.0,
                    0.0,
                    1.0,
                    0.27
                ],
                [
                    0.0,
                    0.0,
                    0.0,
                    1.0
                ]
            ],
            "size": [
                0.52,
                1.16,
                0.6
            ]
        },
        "collider2": {
            "type": "Box",
            "collider2origin": [
                [
                    0.41794797548152757,
                    -0.6874161585807079,
                    -0.5939516097402511,
                    0.0018090081761367172
                ],
                [
                    -0.395585572966582,
                    -0.7262637433389149,
                    0.5621859386111037,
                    0.8419148044646755
                ],
                [
                    -0.8178212177802635,
                    -5.787033172304953e-06,
                    -0.5754723761527712,
                    -0.2752442090068187
                ],
                [
                    0.0,
                    0.0,
                    0.0,
                    1.0
                ]
            ],
            "size": [
                0.15068,
                0.17726,
                0.74884
            ]
        },
        "distance": 0.4628668995212986
    },
    {
        "case": 10,
        "collider1": {
            "type": "Box",
            "collider2origin": [
                [
                    0.9077781725128689,
                    0.4194505805326724,
                    0.0,
                    0.4158817547107895
                ],
                [
                    -0.4194505805326724,
                    0.9077781725128689,
                    0.0,
                    0.733173894971941
                ],
                [
                    0.0,
                    0.0,
                    1.0,
                    -0.6599999999999999
                ],
                [
                    0.0,
                    0.0,
                    0.0,
                    1.0
                ]
            ],
            "size": [
                0.6,
                1.0,
                0.8
            ]
        },
        "collider2": {
            "type": "Box",
            "collider2origin": [
                [
                    0.6852670892903414,
                    -0.6874148605062816,
                    -0.24056148047988155,
                    -0.1641313490871512
                ],
                [
                    -0.6486068226579071,
                    -0.7262649719655792,
                    0.22770239370162676,
                    1.1729387212271047
                ],
                [
                    -0.33123738608006964,
                    -7.139048419011926e-06,
                    -0.9435474519131916,
                    -0.7194295345482034
                ],
                [
                    0.0,
                    0.0,
                    0.0,
                    1.0
                ]
            ],
            "size": [
                0.1202,
                0.13634,
                0.67816
            ]
        },
        "distance": 0.22904042957653498
    },
    {
        "case": 11,
        "collider1": {
            "type": "Box",
            "collider2origin": [
                [
                    0.907778172512869,
                    0.4194505805326725,
                    0.0,
                    -1.612083837096907
                ],
                [
                    -0.4194505805326725,
                    0.907778172512869,
                    0.0,
                    -0.24654756573714753
                ],
                [
                    0.0,
                    0.0,
                    1.0,
                    -0.040000000000000036
                ],
                [
                    0.0,
                    0.0,
                    0.0,
                    1.0
                ]
            ],
            "size": [
                2.0,
                2.0,
                2.0
            ]
        },
        "collider2": {
            "type": "Box",
            "collider2origin": [
                [
                    0.6852670892903414,
                    -0.6874148605062816,
                    -0.24056148047988155,
                    -0.1641313490871512
                ],
                [
                    -0.6486068226579071,
                    -0.7262649719655792,
                    0.22770239370162676,
                    1.1729387212271047
                ],
                [
                    -0.33123738608006964,
                    -7.139048419011926e-06,
                    -0.9435474519131916,
                    -0.7194295345482034
                ],
                [
                    0.0,
                    0.0,
                    0.0,
                    1.0
                ]
            ],
            "size": [
                0.1202,
                0.13634,
                0.67816
            ]
        },
        "distance": 0.7773376539578147
    },
    {
        "case": 12,
        "collider1": {
            "type": "Cylinder",
            "collider2origin": [
                [
                    0.907778172512869,
                    0.4194505805326725,
                    0.0,
                    -0.07232761537572224
                ],
                [
                    -0.4194505805326725,
                    0.907778172512869,
                    0.0,
                    1.2000044650142188
                ],
                [
                    0.0,
                    0.0,
                    1.0,
                    -0.5800000000000001
                ],
                [
                    0.0,
                    0.0,
                    0.0,
                    1.0
                ]
            ],
            "radius": 0.04,
            "height": 0.96
        },
        "collider2": {
            "type": "Box",
            "collider2origin": [
                [
                    0.6852670892903414,
                    -0.6874148605062816,
                    -0.24056148047988155,
                    -0.1641313490871512
                ],
                [
                    -0.6486068226579071,
                    -0.7262649719655792,
                    0.22770239370162676,
                    1.1729387212271047
                ],
                [
                    -0.33123738608006964,
                    -7.139048419011926e-06,
                    -0.9435474519131916,
                    -0.7194295345482034
                ],
                [
                    0.0,
                    0.0,
                    0.0,
                    1.0
                ]
            ],
            "size": [
                0.1202,
                0.13634,
                0.67816
            ]
        },
        "distance": 0.0
    }
]