[
    {
        "case": 0,
        "collider1": {
            "type": "Box",
            "collider2origin": [
                [
                    0.9077781725128689,
                    0.4194505805326724,
                    0.0,
                    0.4158817547107895
                ],
                [
                    -0.4194505805326724,
                    0.9077781725128689,
                    0.0,
                    0.733173894971941
                ],
                [
                    0.0,
                    0.0,
                    1.0,
                    -0.6599999999999999
                ],
                [
                    0.0,
                    0.0,
                    0.0,
                    1.0
                ]
            ],
            "size": [
                0.6,
                1.0,
                0.8
            ]
        },
        "collider2": {
            "type": "Box",
            "collider2origin": [
                [
                    0.6474686549073393,
                    0.6405858946031782,
                    -0.4128365930340075,
                    0.2879062061383357
                ],
                [
                    0.5401357039647054,
                    -0.7678865225992754,
                    -0.3443888931323782,
                    0.5626127062254862
                ],
                [
                    -0.5376223230252191,
                    -6.770399365953415e-06,
                    -0.843185767040175,
                    -0.3555779061215989
                ],
                [
                    0.0,
                    0.0,
                    0.0,
                    1.0
                ]
            ],
            "size": [
                0.15068,
                0.17726,
                0.74884
            ]
        },
        "distance": 0.0
    },
    {
        "case": 1,
        "collider1": {
            "type": "Box",
            "collider2origin": [
                [
                    0.9077781725128689,
                    0.4194505805326724,
                    0.0,
                    0.27063700059322826
                ],
                [
                    -0.4194505805326724,
                    0.9077781725128689,
                    0.0,
                    0.8002854543438492
                ],
                [
                    0.0,
                    0.0,
                    1.0,
                    -0.25
                ],
                [
                    0.0,
                    0.0,
                    0.0,
                    1.0
                ]
            ],
            "size": [
                0.2,
                0.2,
                0.02
            ]
        },
        "collider2": {
            "type": "Box",
            "collider2origin": [
                [
                    0.6474686549073393,
                    0.6405858946031782,
                    -0.4128365930340075,
                    0.2879062061383357
                ],
                [
                    0.5401357039647054,
                    -0.7678865225992754,
                    -0.3443888931323782,
                    0.5626127062254862
                ],
                [
                    -0.5376223230252191,
                    -6.770399365953415e-06,
                    -0.843185767040175,
                    -0.3555779061215989
                ],
                [
                    0.0,
                    0.0,
                    0.0,
                    1.0
                ]
            ],
            "size": [
                0.15068,
                0.17726,
                0.74884
            ]
        },
        "distance": 0.0
    },
    {
        "case": 2,
        "collider1": {
            "type": "Box",
            "collider2origin": [
                [
                    0.907778172512869,
                    0.4194505805326725,
                    0.0,
                    0.9947946797881562
                ],
                [
                    -0.4194505805326725,
                    0.907778172512869,
                    0.0,
                    0.5317739604993647
                ],
                [
                    0.0,
                    0.0,
                    1.0,
                    -0.69
                ],
                [
                    0.0,
                    0.0,
                    0.0,
                    1.0
                ]
            ],
            "size": [
                0.6,
                1.2,
                0.75
            ]
        },
        "collider2": {
            "type": "Box",
            "collider2origin": [
                [
                    0.6474686549073393,
                    0.6405858946031782,
                    -0.4128365930340075,
                    0.2879062061383357
                ],
                [
                    0.5401357039647054,
                    -0.7678865225992754,
                    -0.3443888931323782,
                    0.5626127062254862
                ],
                [
                    -0.5376223230252191,
                    -6.770399365953415e-06,
                    -0.843185767040175,
                    -0.3555779061215989
                ],
                [
                    0.0,
                    0.0,
                    0.0,
                    1.0
                ]
            ],
            "size": [
                0.15068,
                0.17726,
                0.74884
            ]
        },
        "distance": 0.21722965672325154
    },
    {
        "case": 3,
        "collider1": {
            "type": "Box",
            "collider2origin": [
                [
                    0.9077781725128689,
                    0.4194505805326724,
                    0.0,
                    0.4158817547107895
                ],
                [
                    -0.4194505805326724,
                    0.9077781725128689,
                    0.0,
                    0.733173894971941
                ],
                [
                    0.0,
                    0.0,
                    1.0,
                    -0.6599999999999999
                ],
                [
                    0.0,
                    0.0,
                    0.0,
                    1.0
                ]
            ],
            "size": [
                0.6,
                1.0,
                0.8
            ]
        },
        "collider2": {
            "type": "Box",
            "collider2origin": [
                [
                    0.6474686549073393,
                    0.6405858946031782,
                    -0.4128365930340075,
                    0.2879062061383357
                ],
                [
                    0.5401357039647054,
                    -0.7678865225992754,
                    -0.3443888931323782,
                    0.5626127062254862
                ],
                [
                    -0.5376223230252191,
                    -6.770399365953415e-06,
                    -0.843185767040175,
                    -0.3555779061215989
                ],
                [
                    0.0,
                    0.0,
                    0.0,
                    1.0
                ]
            ],
            "size": [
                0.15068,
                0.17726,
                0.74884
            ]
        },
        "distance": 0.0
    },
    {
        "case": 4,
        "collider1": {
            "type": "Box",
            "collider2origin": [
                [
                    0.9077781725128689,
                    0.4194505805326724,
                    0.0,
                    0.27063700059322826
                ],
                [
                    -0.4194505805326724,
                    0.9077781725128689,
                    0.0,
                    0.8002854543438492
                ],
                [
                    0.0,
                    0.0,
                    1.0,
                    -0.25
                ],
                [
                    0.0,
                    0.0,
                    0.0,
                    1.0
                ]
            ],
            "size": [
                0.2,
                0.2,
                0.02
            ]
        },
        "collider2": {
            "type": "Box",
            "collider2origin": [
                [
                    0.6474686549073393,
                    0.6405858946031782,
                    -0.4128365930340075,
                    0.2879062061383357
                ],
                [
                    0.5401357039647054,
                    -0.7678865225992754,
                    -0.3443888931323782,
                    0.5626127062254862
                ],
                [
                    -0.5376223230252191,
                    -6.770399365953415e-06,
                    -0.843185767040175,
                    -0.3555779061215989
                ],
                [
                    0.0,
                    0.0,
                    0.0,
                    1.0
                ]
            ],
            "size": [
                0.15068,
                0.17726,
                0.74884
            ]
        },
        "distance": 0.0
    },
    {
        "case": 5,
        "collider1": {
            "type": "Box",
            "collider2origin": [
                [
                    0.907778172512869,
                    0.4194505805326725,
                    0.0,
                    0.9947946797881562
                ],
                [
                    -0.4194505805326725,
                    0.907778172512869,
                    0.0,
                    0.5317739604993647
                ],
                [
                    0.0,
                    0.0,
                    1.0,
                    -0.69
                ],
                [
                    0.0,
                    0.0,
                    0.0,
                    1.0
                ]
            ],
            "size": [
                0.6,
                1.2,
                0.75
            ]
        },
        "collider2": {
            "type": "Box",
            "collider2origin": [
                [
                    0.6474686549073393,
                    0.6405858946031782,
                    -0.4128365930340075,
                    0.2879062061383357
                ],
                [
                    0.5401357039647054,
                    -0.7678865225992754,
                    -0.3443888931323782,
                    0.5626127062254862
                ],
                [
                    -0.5376223230252191,
                    -6.770399365953415e-06,
                    -0.843185767040175,
                    -0.3555779061215989
                ],
                [
                    0.0,
                    0.0,
                    0.0,
                    1.0
                ]
            ],
            "size": [
                0.15068,
                0.17726,
                0.74884
            ]
        },
        "distance": 0.21722965672325154
    },
    {
        "case": 6,
        "collider1": {
            "type": "Box",
            "collider2origin": [
                [
                    0.9077781725128689,
                    0.4194505805326724,
                    0.0,
                    0.4158817547107895
                ],
                [
                    -0.4194505805326724,
                    0.9077781725128689,
                    0.0,
                    0.733173894971941
                ],
                [
                    0.0,
                    0.0,
                    1.0,
                    -0.6599999999999999
                ],
                [
                    0.0,
                    0.0,
                    0.0,
                    1.0
                ]
            ],
            "size": [
                0.6,
                1.0,
                0.8
            ]
        },
        "collider2": {
            "type": "Box",
            "collider2origin": [
                [
                    0.28708958066347656,
                    0.6405847949752052,
                    -0.7122013009824142,
                    -0.1214900499669403
                ],
                [
                    0.23950111845353853,
                    -0.7678874399422789,
                    -0.5941280113228099,
                    0.3856165534816128
                ],
                [
                    -0.9274798040571951,
                    -5.046518262636763e-06,
                    -0.37387325799067156,
                    -0.7234974296220226
                ],
                [
                    0.0,
                    0.0,
                    0.0,
                    1.0
                ]
            ],
            "size": [
                0.1202,
                0.13634,
                0.67816
            ]
        },
        "distance": 0.0
    },
    {
        "case": 7,
        "collider1": {
            "type": "Box",
            "collider2origin": [
                [
                    0.907778172512869,
                    0.4194505805326725,
                    0.0,
                    -1.612083837096907
                ],
                [
                    -0.4194505805326725,
                    0.907778172512869,
                    0.0,
                    -0.24654756573714753
                ],
                [
                    0.0,
                    0.0,
                    1.0,
                    -0.040000000000000036
                ],
                [
                    0.0,
                    0.0,
                    0.0,
                    1.0
                ]
            ],
            "size": [
                2.0,
                2.0,
                2.0
            ]
        },
        "collider2": {
            "type": "Box",
            "collider2origin": [
                [
                    0.28708958066347656,
                    0.6405847949752052,
                    -0.7122013009824142,
                    -0.1214900499669403
                ],
                [
                    0.23950111845353853,
                    -0.7678874399422789,
                    -0.5941280113228099,
                    0.3856165534816128
                ],
                [
                    -0.9274798040571951,
                    -5.046518262636763e-06,
                    -0.37387325799067156,
                    -0.7234974296220226
                ],
                [
                    0.0,
                    0.0,
                    0.0,
                    1.0
                ]
            ],
            "size": [
                0.1202,
                0.13634,
                0.67816
            ]
        },
        "distance": 0.0
    },
    {
        "case": 8,
        "collider1": {
            "type": "Box",
            "collider2origin": [
                [
                    0.907778172512869,
                    0.4194505805326725,
                    0.0,
                    -1.612083837096907
                ],
                [
                    -0.4194505805326725,
                    0.907778172512869,
                    0.0,
                    -0.24654756573714753
                ],
                [
                    0.0,
                    0.0,
                    1.0,
                    -0.040000000000000036
                ],
                [
                    0.0,
                    0.0,
                    0.0,
                    1.0
                ]
            ],
            "size": [
                2.0,
                2.0,
                2.0
            ]
        },
        "collider2": {
            "type": "Box",
            "collider2origin": [
                [
                    0.5823333707193736,
                    0.6405855724590956,
                    -0.5005376806034337,
                    -0.25918844470129937
                ],
                [
                    0.48579890933202835,
                    -0.7678867913407132,
                    -0.41755154816654133,
                    0.1252033623855563
                ],
                [
                    -0.6518337710171391,
                    -6.458823816374817e-06,
                    -0.7583618759667835,
                    -0.8345348913640331
                ],
                [
                    0.0,
                    0.0,
                    0.0,
                    1.0
                ]
            ],
            "size": [
                0.09102,
                0.10007,
                0.11882
            ]
        },
        "distance": 0.0
    },
    {
        "case": 9,
        "collider1": {
            "type": "Box",
            "collider2origin": [
                [
                    0.907778172512869,
                    0.4194505805326725,
                    0.0,
                    -1.612083837096907
                ],
                [
                    -0.4194505805326725,
                    0.907778172512869,
                    0.0,
                    -0.24654756573714753
                ],
                [
                    0.0,
                    0.0,
                    1.0,
                    -0.040000000000000036
                ],
                [
                    0.0,
                    0.0,
                    0.0,
                    1.0
                ]
            ],
            "size": [
                2.0,
                2.0,
                2.0
            ]
        },
        "collider2": {
            "type": "Box",
            "collider2origin": [
                [
                    -0.1339783426410584,
                    0.8552846508615068,
                    -0.5005376806034337,
                    -0.3094152534280435
                ],
                [
                    0.9028032862904883,
                    -0.10294139539961139,
                    -0.41755154816654133,
                    0.07640754476209222
                ],
                [
                    -0.40865147738170454,
                    -0.5078299273515601,
                    -0.7583618759667835,
                    -0.918709489093614
                ],
                [
                    0.0,
                    0.0,
                    0.0,
                    1.0
                ]
            ],
            "size": [
                0.09126,
                0.11887,
                0.10009
            ]
        },
        "distance": 0.0
    },
    {
        "case": 10,
        "collider1": {
            "type": "Box",
            "collider2origin": [
                [
                    0.907778172512869,
                    0.4194505805326725,
                    0.0,
                    -1.612083837096907
                ],
                [
                    -0.4194505805326725,
                    0.907778172512869,
                    0.0,
                    -0.24654756573714753
                ],
                [
                    0.0,
                    0.0,
                    1.0,
                    -0.040000000000000036
                ],
                [
                    0.0,
                    0.0,
                    0.0,
                    1.0
                ]
            ],
            "size": [
                2.0,
                2.0,
                2.0
            ]
        },
        "collider2": {
            "type": "Box",
            "collider2origin": [
                [
                    -0.35698838054558596,
                    0.8552878689315653,
                    0.37555553173124834,
                    -0.24705741037766432
                ],
                [
                    -0.8274176370820858,
                    -0.1029418895192515,
                    -0.5520715725589425,
                    0.06657473473712516
                ],
                [
                    -0.433519722735814,
                    -0.5078244072912476,
                    0.7444293259661089,
                    -0.9587506285729573
                ],
                [
                    0.0,
                    0.0,
                    0.0,
                    1.0
                ]
            ],
            "size": [
                0.08993,
                0.0305,
                0.09007
            ]
        },
        "distance": 0.06848716582103839
    }
]