[
    {
        "case": 0,
        "collider1": {
            "type": "Box",
            "collider2origin": [
                [
                    1.0,
                    0.0,
                    0.0,
                    0.7
                ],
                [
                    0.0,
                    1.0,
                    0.0,
                    -0.15085999999999994
                ],
                [
                    0.0,
                    0.0,
                    1.0,
                    -1.03301
                ],
                [
                    0.0,
                    0.0,
                    0.0,
                    1.0
                ]
            ],
            "size": [
                0.6,
                0.06,
                0.06
            ]
        },
        "collider2": {
            "type": "Box",
            "collider2origin": [
                [
                    0.00807742772401242,
                    -0.9999576382835733,
                    -0.004413252734831671,
                    0.9457316836820021
                ],
                [
                    -0.8771615505735063,
                    -0.009204433214081417,
                    0.4801071678330682,
                    -0.34087052264882467
                ],
                [
                    -0.4801274511594246,
                    -6.895335994192964e-06,
                    -0.8771987406486675,
                    -0.9332760446339554
                ],
                [
                    0.0,
                    0.0,
                    0.0,
                    1.0
                ]
            ],
            "size": [
                0.1202,
                0.13634,
                0.67816
            ]
        },
        "distance": 0.01752789643322816
    },
    {
        "case": 1,
        "collider1": {
            "type": "Box",
            "collider2origin": [
                [
                    1.0,
                    0.0,
                    0.0,
                    1.2009999999999998
                ],
                [
                    0.0,
                    1.0,
                    0.0,
                    0.02914
                ],
                [
                    0.0,
                    0.0,
                    1.0,
                    -1.22801
                ],
                [
                    0.0,
                    0.0,
                    0.0,
                    1.0
                ]
            ],
            "size": [
                0.41,
                0.6,
                0.82
            ]
        },
        "collider2": {
            "type": "Box",
            "collider2origin": [
                [
                    0.00807742772401242,
                    -0.9999576382835733,
                    -0.004413252734831671,
                    0.9457316836820021
                ],
                [
                    -0.8771615505735063,
                    -0.009204433214081417,
                    0.4801071678330682,
                    -0.34087052264882467
                ],
                [
                    -0.4801274511594246,
                    -6.895335994192964e-06,
                    -0.8771987406486675,
                    -0.9332760446339554
                ],
                [
                    0.0,
                    0.0,
                    0.0,
                    1.0
                ]
            ],
            "size": [
                0.1202,
                0.13634,
                0.67816
            ]
        },
        "distance": 0.0
    },
    {
        "case": 2,
        "collider1": {
            "type": "Box",
            "collider2origin": [
                [
                    1.0,
                    0.0,
                    0.0,
                    0.7
                ],
                [
                    0.0,
                    1.0,
                    0.0,
                    -0.15085999999999994
                ],
                [
                    0.0,
                    0.0,
                    1.0,
                    -1.03301
                ],
                [
                    0.0,
                    0.0,
                    0.0,
                    1.0
                ]
            ],
            "size": [
                0.6,
                0.06,
                0.06
            ]
        },
        "collider2": {
            "type": "Box",
            "collider2origin": [
                [
                    -0.29399087537882124,
                    -0.9558008004678273,
                    0.0037676277755277505,
                    0.8270499117890473
                ],
                [
                    0.8716684434255366,
                    -0.2697259407193806,
                    -0.4091968250599553,
                    -0.2481948374535624
                ],
                [
                    0.3921268798872335,
                    -0.11701601056310955,
                    0.9124383613931394,
                    -1.0874684757331636
                ],
                [
                    0.0,
                    0.0,
                    0.0,
                    1.0
                ]
            ],
            "size": [
                0.09126,
                0.11887,
                0.10009
            ]
        },
        "distance": 0.010360754698947382
    }
]